conductor_grpc/__init__.py
conductor_grpc/event_service_pb2.py
conductor_grpc/event_service_pb2_grpc.py
conductor_grpc/metadata_service_pb2.py
conductor_grpc/metadata_service_pb2_grpc.py
conductor_grpc/search_pb2.py
conductor_grpc/search_pb2_grpc.py
conductor_grpc/task_service_pb2.py
conductor_grpc/task_service_pb2_grpc.py
conductor_grpc/workflow_service_pb2.py
conductor_grpc/workflow_service_pb2_grpc.py
conductor_grpc-0.0.4.dist-info/METADATA
conductor_grpc-0.0.4.dist-info/WHEEL
conductor_grpc-0.0.4.dist-info/top_level.txt
conductor_grpc-0.0.4.dist-info/RECORD
